[{
  "_id": {
    "$oid": "662b02a25d88e0d742bfb07d"
  },
  "nombre": "MEMORIA RAM DDR4 8GB",
  "precio": 80000,
  "imagen": "Nn9HWvYCL.jpeg",
  "__v": 0
},
{
  "_id": {
    "$oid": "662b040f5d88e0d742c05398"
  },
  "nombre": "BOARD GIGABYTE B450M",
  "precio": 391000,
  "imagen": "Xigpc4EHB.jpeg",
  "__v": 0
},
{
  "_id": {
    "$oid": "662b047e5d88e0d742c08d6b"
  },
  "nombre": "NVIDIA GEFORCE 4060 TI",
  "precio": 3650000,
  "imagen": "yDNzugzcx.jpeg",
  "__v": 0
},
{
  "_id": {
    "$oid": "662b04fb5d88e0d742c0ca87"
  },
  "nombre": "M.2 250GB KINGSTON /PCIE",
  "precio": 158000,
  "imagen": "PS5aH836V.jpeg",
  "__v": 0
},
{
  "_id": {
    "$oid": "662b056c5d88e0d742c100d7"
  },
  "nombre": "INTEL CORE I5 12400",
  "precio": 1129000,
  "imagen": "g7O_4QZ-4.jpeg",
  "__v": 0
},
{
  "_id": {
    "$oid": "662b061c5d88e0d742c150d1"
  },
  "nombre": "TECLADO LOGITECH K500",
  "precio": 169000,
  "imagen": "t3bP2DIFJ.jpeg",
  "__v": 0
},
{
  "_id": {
    "$oid": "662b06675d88e0d742c17b33"
  },
  "nombre": "CAJA COOLER MASTER Q300L",
  "precio": 275000,
  "imagen": "IVK_5ji6S.jpeg",
  "__v": 0
},
{
  "_id": {
    "$oid": "662b080f5d88e0d742c279ff"
  },
  "nombre": "512GB ADATA ASU650",
  "precio": 206000,
  "imagen": "pt6fEPZWQ.jpeg",
  "__v": 0
}]